pytaxa/__init__.py
pytaxa/ranks_ref.py
pytaxa/utils.py
pytaxa/constructors/__init__.py
pytaxa/constructors/constructors.py
pytaxa/constructors/taxa.py
pytaxa/examples/__init__.py
pytaxa/examples/eg.py
pytaxa/taxa/__init__.py
pytaxa/taxa/hierarchies.py
pytaxa/taxa/hierarchy.py
pytaxa/taxa/taxa.py
pytaxa/taxa/taxon.py
pytaxa/taxa/taxonomy.py
pytaxa-0.0.6.dist-info/METADATA
pytaxa-0.0.6.dist-info/RECORD
pytaxa-0.0.6.dist-info/WHEEL
pytaxa-0.0.6.dist-info/top_level.txt
